django_liveload-0.1.1.dist-info/licenses/LICENSE
liveload/__init__.py
liveload/consumers.py
liveload/progress.py
liveload/routing.py
liveload/utils.py
liveload/management/__init__.py
liveload/management/commands/__init__.py
liveload/management/commands/runlive.py
django_liveload-0.1.1.dist-info/METADATA
django_liveload-0.1.1.dist-info/WHEEL
django_liveload-0.1.1.dist-info/top_level.txt
django_liveload-0.1.1.dist-info/RECORD
